LICENSE
MANIFEST.in
README.md
sender.py
sender_psutil.py
setup.py
djangovisor/__init__.py
djangovisor/models.py
djangovisor/urls.py
djangovisor/views.py
djangovisor.egg-info/PKG-INFO
djangovisor.egg-info/SOURCES.txt
djangovisor.egg-info/dependency_links.txt
djangovisor.egg-info/pbr.json
djangovisor.egg-info/top_level.txt
djangovisor/static/css/bootstrap.min.css
djangovisor/static/css/djangovisor.css
djangovisor/static/css/img/noise.png
djangovisor/static/js/csrf.js
djangovisor/static/js/dygraph-combined.js
djangovisor/static/js/jquery-2.1.4.min.js
djangovisor/templates/base.html
djangovisor/templates/djangovisor/confirm_delete.html
djangovisor/templates/djangovisor/dashboard.html
djangovisor/templates/djangovisor/error.html
djangovisor/templates/djangovisor/process.html
djangovisor/templates/djangovisor/server.html
djangovisor/templates/djangovisor/includes/dashboard_table.html
djangovisor/templates/djangovisor/includes/process_buttons.html
djangovisor/templates/djangovisor/includes/process_log.html
djangovisor/templates/djangovisor/includes/process_table.html
djangovisor/templates/djangovisor/includes/server_log.html
djangovisor/templates/djangovisor/includes/server_table.html
djangovisor/templatetags/__init__.py
djangovisor/templatetags/djangovisor_tags.py