Metadata-Version: 1.1
Name: djangovisor
Version: 0.9
Summary: This app collects data from supervisor instances on one or multiple servers, stores and visualizes it.
Home-page: http://djangovisor.cfs-me-research.net/djangovisor/
Author: Nicor Lengert
Author-email: nicorlengert@gmx.de
License: BSD License
Platform: UNKNOWN
Classifier: Environment :: Web Environment
Classifier: Framework :: Django
Classifier: Intended Audience :: Developers
Classifier: License :: OSI Approved :: BSD License
Classifier: Operating System :: OS Independent
Classifier: Programming Language :: Python
Classifier: Programming Language :: Python :: 2.7
Classifier: Programming Language :: Python :: 3
Classifier: Programming Language :: Python :: 3.2
Classifier: Programming Language :: Python :: 3.3
Classifier: Topic :: Internet :: WWW/HTTP
Classifier: Topic :: Internet :: WWW/HTTP :: Dynamic Content
